minmo/__init__.py
minmo/claude_wrapper.py
minmo/cli.py
minmo/gemini_cli_wrapper.py
minmo/indexer.py
minmo/orchestrator.py
minmo/py.typed
minmo/scribe_mcp.py
minmo_engine-1.3.1.dist-info/licenses/LICENSE
minmo_engine-1.3.1.dist-info/METADATA
minmo_engine-1.3.1.dist-info/WHEEL
minmo_engine-1.3.1.dist-info/entry_points.txt
minmo_engine-1.3.1.dist-info/top_level.txt
minmo_engine-1.3.1.dist-info/RECORD
