Metadata-Version: 2.4
Name: minmo-engine
Version: 1.3.1
Summary: MCP 통합 자동화 프레임워크 - Claude Code와 Gemini를 연동한 멀티 에이전트 오케스트레이션
Home-page: https://github.com/minmo/minmo-engine
Author: Minmo Team
Author-email: Minmo Team <minmo@example.com>
Maintainer-email: Minmo Team <minmo@example.com>
License: MIT
Project-URL: Homepage, https://github.com/minmo/minmo-engine
Project-URL: Documentation, https://github.com/minmo/minmo-engine#readme
Project-URL: Repository, https://github.com/minmo/minmo-engine.git
Project-URL: Issues, https://github.com/minmo/minmo-engine/issues
Project-URL: Changelog, https://github.com/minmo/minmo-engine/blob/main/CHANGELOG.md
Keywords: mcp,automation,claude,gemini,orchestration,agent,ai,llm,code-generation
Classifier: Development Status :: 4 - Beta
Classifier: Environment :: Console
Classifier: Intended Audience :: Developers
Classifier: License :: OSI Approved :: MIT License
Classifier: Operating System :: OS Independent
Classifier: Programming Language :: Python :: 3
Classifier: Programming Language :: Python :: 3.9
Classifier: Programming Language :: Python :: 3.10
Classifier: Programming Language :: Python :: 3.11
Classifier: Programming Language :: Python :: 3.12
Classifier: Topic :: Software Development
Classifier: Topic :: Software Development :: Code Generators
Classifier: Topic :: Software Development :: Libraries :: Python Modules
Classifier: Typing :: Typed
Requires-Python: >=3.9
License-File: LICENSE
Requires-Dist: fastmcp>=0.1.0
Requires-Dist: redis>=5.0.0
Requires-Dist: rich>=13.0.0
Requires-Dist: pexpect>=4.8.0
Requires-Dist: watchdog>=3.0.0
Requires-Dist: pyyaml>=6.0
Requires-Dist: typing-extensions>=4.0.0
Requires-Dist: prompt_toolkit>=3.0.0
Provides-Extra: dev
Requires-Dist: pytest>=7.0.0; extra == "dev"
Requires-Dist: pytest-asyncio>=0.21.0; extra == "dev"
Requires-Dist: pytest-cov>=4.0.0; extra == "dev"
Requires-Dist: pytest-mock>=3.12.0; extra == "dev"
Requires-Dist: black>=23.0.0; extra == "dev"
Requires-Dist: ruff>=0.1.0; extra == "dev"
Requires-Dist: mypy>=1.0.0; extra == "dev"
Provides-Extra: vector
Requires-Dist: chromadb>=0.4.0; extra == "vector"
Requires-Dist: sentence-transformers>=2.2.0; extra == "vector"
Dynamic: author
Dynamic: home-page
Dynamic: license-file
Dynamic: requires-python
